secretctl/__init__.py
secretctl/cli.py
secretctl/main.py
secretctl/output.py
secretctl/tuples.py
secretctl/validators.py
secretctl-0.0.19.dist-info/LICENSE
secretctl-0.0.19.dist-info/METADATA
secretctl-0.0.19.dist-info/WHEEL
secretctl-0.0.19.dist-info/entry_points.txt
secretctl-0.0.19.dist-info/top_level.txt
secretctl-0.0.19.dist-info/RECORD
