Metadata-Version: 2.1
Name: secretctl
Version: 0.0.19
Summary: Command line tool for working with aws secrets manager
Home-page: https://github.com/ncheneweth/secretctl
Author: Nic Cheneweth
Author-email: nic.cheneweth@thoughtworks.com
License: UNKNOWN
Platform: UNKNOWN
Classifier: Programming Language :: Python :: 3
Classifier: License :: OSI Approved :: MIT License
Classifier: Operating System :: POSIX :: Linux
Classifier: Development Status :: 3 - Alpha
Requires-Python: >=3.5
Requires-Dist: invoke (==1.3.0)
Requires-Dist: boto3 (==1.9.226)
Requires-Dist: pyyaml (==5.1.2)
Requires-Dist: requests (==2.22.0)
Requires-Dist: colorama (==0.4.1)
